{
  "pensamentos": [
    {
      "id": 1,
      "conteudo": "Que bom que você veio",
      "autoria": "Queixo",
      "modelo": "modelo1",
      "favorito": false
    },
    {
      "id": 2,
      "conteudo": "Teste do modelo 2",
      "autoria": "Dev 2",
      "modelo": "modelo2",
      "favorito": false
    },
    {
      "id": 3,
      "conteudo": "EDITADO",
      "autoria": "EDITADO DE VERDADEDEDEDEDE",
      "modelo": "modelo3",
      "favorito": false
    },
    {
      "conteudo": "qweeq",
      "autoria": "qeqweq",
      "modelo": "modelo1",
      "favorito": false,
      "id": 4
    },
    {
      "conteudo": "aaaaaaaaaa",
      "autoria": "aaaaaaaaaaaaa",
      "modelo": "modelo1",
      "favorito": false,
      "id": 5
    }
  ]
}
